pytest_stats/__init__.py
pytest_stats/default_text_reporter.py
pytest_stats/hooks.py
pytest_stats/py.typed
pytest_stats/pytest_stats.py
pytest_stats/reporters_registry.py
pytest_stats/test_item_data.py
pytest_stats/test_session_data.py
pytest_stats-1.0.1.dist-info/LICENSE
pytest_stats-1.0.1.dist-info/METADATA
pytest_stats-1.0.1.dist-info/WHEEL
pytest_stats-1.0.1.dist-info/entry_points.txt
pytest_stats-1.0.1.dist-info/RECORD
