Metadata-Version: 2.1
Name: pytest-stats
Version: 1.0.1
Summary: Collects tests metadata for future analysis, easy to extend for any data store
Home-page: https://github.com/amitwer/pytest-stats
License: MIT
Keywords: pytest,stats,metadata
Author: Amit Wertheimer
Author-email: 12250123+amitwer@users.noreply.github.com
Requires-Python: >=3.8
Classifier: Framework :: Pytest
Classifier: License :: OSI Approved :: MIT License
Classifier: Programming Language :: Python
Classifier: Programming Language :: Python :: 3
Classifier: Programming Language :: Python :: 3.8
Classifier: Programming Language :: Python :: 3.9
Classifier: Programming Language :: Python :: 3.10
Classifier: Programming Language :: Python :: 3.11
Classifier: Programming Language :: Python :: 3.12
Requires-Dist: pytest (>=8.0.0)
